nodify/__init__.py
nodify/_env.py
nodify/context.py
nodify/conversions.py
nodify/errors.py
nodify/file_nodes.py
nodify/node.py
nodify/operators.py
nodify/parse.py
nodify/registry.py
nodify/syntax_nodes.py
nodify/utils.py
nodify/workflow.py
nodify/cli/_click.py
nodify/cli/_typer.py
nodify/cli/tools.py
nodify/gui/__init__.py
nodify/gui/cli.py
nodify/gui/build/apple-touch-icon.png
nodify/gui/build/asset-manifest.json
nodify/gui/build/favicon-32x32.png
nodify/gui/build/favicon.ico
nodify/gui/build/icon.icns
nodify/gui/build/index.html
nodify/gui/build/manifest.json
nodify/gui/build/mstile-150x150.png
nodify/gui/build/robots.txt
nodify/gui/build/safari-pinned-tab.svg
nodify/gui/build/static/css/main.b71f9b9d.css
nodify/gui/build/static/css/main.b71f9b9d.css.map
nodify/gui/build/static/js/main.e8c3f4c5.js
nodify/gui/build/static/js/main.e8c3f4c5.js.LICENSE.txt
nodify/gui/build/static/js/main.e8c3f4c5.js.map
nodify/server/__init__.py
nodify/server/app.py
nodify/server/cli.py
nodify/server/json.py
nodify/server/launch.py
nodify/server/pyodide.py
nodify/server/registry.py
nodify/server/session.py
nodify/server/sync.py
nodify/server/flask_socketio/__init__.py
nodify/server/flask_socketio/app.py
nodify/server/flask_socketio/emiters.py
nodify/server/flask_socketio/sync.py
nodify/server/flask_socketio/user_management.py
nodify/tests/__init__.py
nodify/tests/test_batching.py
nodify/tests/test_context.py
nodify/tests/test_file_nodes.py
nodify/tests/test_node.py
nodify/tests/test_pythonscript.py
nodify/tests/test_registry.py
nodify/tests/test_syntax_nodes.py
nodify/tests/test_utils.py
nodify/tests/test_workflow.py
nodify-0.0.12.dist-info/licenses/LICENSE
nodify-0.0.12.dist-info/METADATA
nodify-0.0.12.dist-info/WHEEL
nodify-0.0.12.dist-info/entry_points.txt
nodify-0.0.12.dist-info/top_level.txt
nodify-0.0.12.dist-info/RECORD
