Metadata-Version: 2.4
Name: nodify
Version: 0.0.12
Summary: Supercharge your functional application with a powerful node system.
Author-email: Pol Febrer <pfebrer96@gmail.com>
Maintainer-email: Pol Febrer <pfebrer96@gmail.com>
License: MIT License
Project-URL: Homepage, https://github.com/pfebrer/nodify
Project-URL: Repository, https://github.com/pfebrer/nodify
Classifier: Programming Language :: Python :: 3.9
Classifier: Programming Language :: Python :: 3.10
Classifier: Programming Language :: Python :: 3.11
Classifier: Programming Language :: Python :: 3.12
Classifier: Operating System :: OS Independent
Requires-Python: >=3.9
License-File: LICENSE
Provides-Extra: scripting
Requires-Dist: black; extra == "scripting"
Requires-Dist: isort; extra == "scripting"
Provides-Extra: files
Requires-Dist: watchdog; extra == "files"
Provides-Extra: test
Requires-Dist: pytest; extra == "test"
Requires-Dist: coverage[toml]; extra == "test"
Requires-Dist: pytest-cov; extra == "test"
Requires-Dist: pytest-env; extra == "test"
Requires-Dist: pytest-faulthandler; extra == "test"
Requires-Dist: black; extra == "test"
Requires-Dist: isort; extra == "test"
Requires-Dist: watchdog; extra == "test"
Provides-Extra: docs
Requires-Dist: sphinx; extra == "docs"
Requires-Dist: sphinx-rtd-theme; extra == "docs"
Requires-Dist: nbsphinx; extra == "docs"
Requires-Dist: pyvis; extra == "docs"
Requires-Dist: networkx; extra == "docs"
Requires-Dist: matplotlib; extra == "docs"
Requires-Dist: ipykernel; extra == "docs"
Requires-Dist: black; extra == "docs"
Requires-Dist: isort; extra == "docs"
Provides-Extra: server
Requires-Dist: simplejson; extra == "server"
Provides-Extra: gui
Requires-Dist: simplejson; extra == "gui"
Requires-Dist: black; extra == "gui"
Requires-Dist: isort; extra == "gui"
Requires-Dist: flask; extra == "gui"
Requires-Dist: flask-socketio>=5.0; extra == "gui"
Requires-Dist: eventlet; extra == "gui"
Dynamic: license-file
